CHANGES.md
MANIFEST.in
README.md
documentation.url
setup.py
app/plotdevice
app/Resources/PlotDevice.icns
app/Resources/PlotDeviceFile.icns
app/Resources/colors.json
app/Resources/viewer.nib
deps/extensions/module.m
deps/extensions/foundry/Vandercook.h
deps/extensions/foundry/Vandercook.m
deps/extensions/io/AnimatedGif.h
deps/extensions/io/AnimatedGif.m
deps/extensions/io/Pages.h
deps/extensions/io/Pages.m
deps/extensions/io/SysAdmin.h
deps/extensions/io/SysAdmin.m
deps/extensions/io/Video.h
deps/extensions/io/Video.m
deps/extensions/pathmatics/gpc.c
deps/extensions/pathmatics/gpc.h
deps/extensions/pathmatics/pathmatics.h
deps/extensions/pathmatics/pathmatics.m
deps/extensions/svg/Makefile
deps/extensions/svg/NSImage+PlotDevice.swift
deps/extensions/svg/Package.swift
deps/extensions/svg/SwiftDraw/Package.swift
deps/extensions/svg/SwiftDraw/SwiftDraw/CGImage+Mask.swift
deps/extensions/svg/SwiftDraw/SwiftDraw/CGPath+Segment.swift
deps/extensions/svg/SwiftDraw/SwiftDraw/CGPattern+Closure.swift
deps/extensions/svg/SwiftDraw/SwiftDraw/CGTextRenderer+Code.swift
deps/extensions/svg/SwiftDraw/SwiftDraw/CommandLine.Arguments.swift
deps/extensions/svg/SwiftDraw/SwiftDraw/CommandLine.Configuration.swift
deps/extensions/svg/SwiftDraw/SwiftDraw/CommandLine.swift
deps/extensions/svg/SwiftDraw/SwiftDraw/DOM.Color.swift
deps/extensions/svg/SwiftDraw/SwiftDraw/DOM.Element.swift
deps/extensions/svg/SwiftDraw/SwiftDraw/DOM.Gradient.swift
deps/extensions/svg/SwiftDraw/SwiftDraw/DOM.Image.swift
deps/extensions/svg/SwiftDraw/SwiftDraw/DOM.Path.swift
deps/extensions/svg/SwiftDraw/SwiftDraw/DOM.Pattern.swift
deps/extensions/svg/SwiftDraw/SwiftDraw/DOM.SVG.swift
deps/extensions/svg/SwiftDraw/SwiftDraw/DOM.Switch.swift
deps/extensions/svg/SwiftDraw/SwiftDraw/DOM.Text.swift
deps/extensions/svg/SwiftDraw/SwiftDraw/DOM.Use.swift
deps/extensions/svg/SwiftDraw/SwiftDraw/DOM.swift
deps/extensions/svg/SwiftDraw/SwiftDraw/Formatter.XML.swift
deps/extensions/svg/SwiftDraw/SwiftDraw/Formatter.swift
plotdevice.egg-info/PKG-INFO
plotdevice.egg-info/SOURCES.txt
plotdevice.egg-info/dependency_links.txt
plotdevice.egg-info/not-zip-safe
plotdevice.egg-info/requires.txt
plotdevice.egg-info/top_level.txt
